Workbook

Sheet Rental Deals Sheet
A1: Deal ID | B1: Client Name | C1: Phone/WhatsApp | D1: ID/Passport | E1: Rental Start Date | F1: Rental End Date | G1: Rental Days | H1: Time of Rental | I1: Car ID | J1: Daily Rate | K1: Total Amount | L1: Deposit | M1: Payment Status | N1: Overdue Days | O1: Contract Signed | P1: Return Condition Notes | Q1: Car Make/Model | R1: Car Status Link | S1: Country
A2: RENT-202606-001 | B2: Ahmed Al-Sayed | C2: +355689464671 | D2: A123456 | E2: 46178 | F2: 46199 | G2: =IF(AND(ISNUMBER(E2), ISNUMBER(F2)), F2 - E2, "") -> 21 | H2: 09:00 P.M | I2: C007 | J2: 2500 | K2: =IFERROR(IF(G2<>"", J2 * G2, ""), "") -> 52500 | L2: 500 | M2: Paid | O2: Yes | P2: Extended clear | Q2: =IFERROR(_xlfn.XLOOKUP(I2, 'Fleet Master'!$A:$A, 'Fleet Master'!$B:$B, "Unknown Vehicle"), "") -> Touran 7Person
A3: RENT-202606-002 | B3: Maria Lopez | C3: +355689464671 | D3: X987654 | E3: 46188 | F3: 46198 | G3: =IF(AND(ISNUMBER(E3), ISNUMBER(F3)), F3 - E3, "") -> 10 | H3: 09:00 P.M | I3: C004 | K3: =IFERROR(IF(G3<>"", J3 * G3, ""), "") -> 0 | L3: 500 | M3: Partial | O3: Yes | P3: Local contract | Q3: =IFERROR(_xlfn.XLOOKUP(I3, 'Fleet Master'!$A:$A, 'Fleet Master'!$B:$B, "Unknown Vehicle"), "") -> Tiquan
A4: RENT-202606-003 | B4: Timur Ivanov | C4: +355689464671 | D4: AN98123 | E4: 46192 | F4: 46197 | G4: =IF(AND(ISNUMBER(E4), ISNUMBER(F4)), F4 - E4, "") -> 5 | H4: 09:00 P.M | I4: C006 | K4: =IFERROR(IF(G4<>"", J4 * G4, ""), "") -> 0 | L4: 500 | M4: Pending | O4: Yes | P4: Pre-authorized | Q4: =IFERROR(_xlfn.XLOOKUP(I4, 'Fleet Master'!$A:$A, 'Fleet Master'!$B:$B, "Unknown Vehicle"), "") -> Opel (Manual)
A5: RENT-202606-004 | B5: John Doe | C5: +355689464671 | D5: DL44112 | E5: 46174 | F5: 46183 | G5: =IF(AND(ISNUMBER(E5), ISNUMBER(F5)), F5 - E5, "") -> 9 | H5: 09:00 P.M | I5: C008 | K5: =IFERROR(IF(G5<>"", J5 * G5, ""), "") -> 0 | L5: 500 | M5: Paid | O5: Yes | P5: Returned early | Q5: =IFERROR(_xlfn.XLOOKUP(I5, 'Fleet Master'!$A:$A, 'Fleet Master'!$B:$B, "Unknown Vehicle"), "") -> Touran 7Person
Q6: =IFERROR(_xlfn.XLOOKUP(I6, 'Fleet Master'!$A:$A, 'Fleet Master'!$B:$B, "Unknown Vehicle"), "") -> 0
Q7: =IFERROR(_xlfn.XLOOKUP(I7, 'Fleet Master'!$A:$A, 'Fleet Master'!$B:$B, "Unknown Vehicle"), "") -> 0

Sheet Fleet Master
A1: Car ID | B1: Make/Model | C1: Year | D1: License Plate | E1: Color | F1: Current Mileage | G1: Status | H1: Current Deal ID | I1: Rental Start Date | J1: Expected Return Date | K1: Next Available Date | L1: Location | M1: Base Daily Rate ($) | N1: Notes | O1: Override Status | P1: Maintenance Costs
A2: C001 | B2: Jetta OL | C2: 2012 | D2: AB069 OL | E2: FÜME | F2: 0 | G2: =IF(O2="Maintenance", "Maintenance", IF(O2="Out of Service", "Out of Service", IF(I2="", "Available", "Rented"))) -> Rented | I2: =TODAY() -> 46191 | J2: =TODAY()+6 -> 46197 | K2: =IF(G2="Rented", IF(ISNUMBER(J2), J2+1, TODAY()), TODAY()) -> 46198 | L2: Airport | M2: 30 | N2: - | R2: Maintenance
A3: C002 | B3: Jetta SA | C3: 2012 | D3: AB853 SA | E3: GRI | F3: 0 | G3: =IF(O3="Maintenance", "Maintenance", IF(O3="Out of Service", "Out of Service", IF(I3="", "Available", "Rented"))) -> Rented | I3: =TODAY() -> 46191 | J3: =TODAY()+6 -> 46197 | K3: =IF(G3="Rented", IF(ISNUMBER(J3), J3+1, TODAY()), TODAY()) -> 46198 | L3: Airport | M3: 30
A4: C003 | B4: Polo | C4: 2012 | D4: AB027UH | E4: BEYAZ | G4: =IF(O4="Maintenance", "Maintenance", IF(O4="Out of Service", "Out of Service", IF(I4="", "Available", "Rented"))) -> Rented | I4: =TODAY() -> 46191 | J4: =TODAY()+4 -> 46195 | K4: =IF(G4="Rented", IF(ISNUMBER(J4), J4+1, TODAY()), TODAY()) -> 46196 | L4: Airport | M4: 30
A5: C004 | B5: Tiquan | C5: 2009 | D5: AB034UH | E5: SİYAH | F5: 0 | G5: =IF(O5="Maintenance", "Maintenance", IF(O5="Out of Service", "Out of Service", IF(I5="", "Available", "Rented"))) -> Rented | I5: =TODAY() -> 46191 | J5: =TODAY()+6 -> 46197 | K5: =IF(G5="Rented", IF(ISNUMBER(J5), J5+1, TODAY()), TODAY()) -> 46198 | L5: Airport | M5: 30
A6: C005 | B6: Toura 6Ri | C6: 2006 | D6: AB-KE | E6: FÜME | G6: =IF(O6="Maintenance", "Maintenance", IF(O6="Out of Service", "Out of Service", IF(I6="", "Available", "Rented"))) -> Rented | I6: 46191 | J6: =TODAY()+1 -> 46192 | K6: =IF(G6="Rented", IF(ISNUMBER(J6), J6+1, TODAY()), TODAY()) -> 46193 | L6: Airport | M6: 40
A7: C006 | B7: Opel (Manual) | C7: 2015 | D7: AB992PD | E7: KAHVE | F7: 0 | G7: =IF(O7="Maintenance", "Maintenance", IF(O7="Out of Service", "Out of Service", IF(I7="", "Available", "Rented"))) -> Rented | I7: 46193 | J7: 46193 | K7: =IF(G7="Rented", IF(ISNUMBER(J7), J7+1, TODAY()), TODAY()) -> 46194 | L7: Airport | M7: 40
A8: C007 | B8: Touran 7Person | C8: 2006 | D8: AB-GF | E8: SİYAH | G8: =IF(O8="Maintenance", "Maintenance", IF(O8="Out of Service", "Out of Service", IF(I8="", "Available", "Rented"))) -> Available | J8: 46193 | K8: =IF(G8="Rented", IF(ISNUMBER(J8), J8+1, TODAY()), TODAY()) -> 46191 | L8: Airport | M8: 40
A9: C008 | B9: Touran 7Person | C9: 2008 | D9: AB-GF | E9: SİYAH | F9: 0 | G9: =IF(O9="Maintenance", "Maintenance", IF(O9="Out of Service", "Out of Service", IF(I9="", "Available", "Rented"))) -> Available | J9: 46193 | K9: =IF(G9="Rented", IF(ISNUMBER(J9), J9+1, TODAY()), TODAY()) -> 46191 | L9: Airport | M9: 40
A10: C009 | B10: Touran 7Person | C10: 2008 | D10: AB-ZR | E10: MAVİ | F10: 0 | G10: =IF(O10="Maintenance", "Maintenance", IF(O10="Out of Service", "Out of Service", IF(I10="", "Available", "Rented"))) -> Available
A11: C010
A12: C011
A13: C012
A14: C013
A15: C014
A16: C015

Sheet Landing Page
A1: FRONT DESK: VEHICLE AVAILABILITY CHECKER
B3: Start Date: | C3: =TODAY()+11 -> 46202 | E3: AVAILABLE VEHICLES: | F3: =IF(A11="No Cars Available", 0, COUNTIF(A11:A100, "?*")) -> 15
B4: No. of Days: | C4: 5
B5: Expected Return: | C5: =IF(AND(ISNUMBER(C3), ISNUMBER(C4)), C3 + C4, "") -> 46207
A10: Car ID | B10: Model/Mark | C10: Color | D10: Number Plate | E10: Price / Day | F10: Total Price
A11: {=IF($C$3="", _xlfn._xlws.FILTER('Fleet Master'!$A$2:$A$100, ('Fleet Master'!$G$2:$G$100="Available") * ('Fleet Master'!$A$2:$A$100<>""), "No Cars Available"), _xlfn._xlws.FILTER('Fleet Master'!$A$2:$A$100, ('Fleet Master'!$K$2:$K$100<=$C$3) * ('Fleet Master'!$G$2:$G$100<>"Out of Service") * ('Fleet Master'!$G$2:$G$100<>"Maintenance") * ('Fleet Master'!$A$2:$A$100<>""), "No Cars Available"))} -> C001 | B11: {=IF($C$3="", _xlfn._xlws.FILTER('Fleet Master'!$B$2:$B$100, ('Fleet Master'!$G$2:$G$100="Available") * ('Fleet Master'!$A$2:$A$100<>""), ""), _xlfn._xlws.FILTER('Fleet Master'!$B$2:$B$100, ('Fleet Master'!$K$2:$K$100<=$C$3) * ('Fleet Master'!$G$2:$G$100<>"Out of Service") * ('Fleet Master'!$G$2:$G$100<>"Maintenance") * ('Fleet Master'!$A$2:$A$100<>""), ""))} -> Jetta OL | C11: {=IF($C$3="", _xlfn._xlws.FILTER('Fleet Master'!$E$2:$E$100, ('Fleet Master'!$G$2:$G$100="Available") * ('Fleet Master'!$A$2:$A$100<>""), ""), _xlfn._xlws.FILTER('Fleet Master'!$E$2:$E$100, ('Fleet Master'!$K$2:$K$100<=$C$3) * ('Fleet Master'!$G$2:$G$100<>"Out of Service") * ('Fleet Master'!$G$2:$G$100<>"Maintenance") * ('Fleet Master'!$A$2:$A$100<>""), ""))} -> FÜME | D11: {=IF($C$3="", _xlfn._xlws.FILTER('Fleet Master'!$D$2:$D$100, ('Fleet Master'!$G$2:$G$100="Available") * ('Fleet Master'!$A$2:$A$100<>""), ""), _xlfn._xlws.FILTER('Fleet Master'!$D$2:$D$100, ('Fleet Master'!$K$2:$K$100<=$C$3) * ('Fleet Master'!$G$2:$G$100<>"Out of Service") * ('Fleet Master'!$G$2:$G$100<>"Maintenance") * ('Fleet Master'!$A$2:$A$100<>""), ""))} -> AB069 OL | E11: {=IF($C$3="", _xlfn._xlws.FILTER('Fleet Master'!$M$2:$M$100, ('Fleet Master'!$G$2:$G$100="Available") * ('Fleet Master'!$A$2:$A$100<>""), ""), _xlfn._xlws.FILTER('Fleet Master'!$M$2:$M$100, ('Fleet Master'!$K$2:$K$100<=$C$3) * ('Fleet Master'!$G$2:$G$100<>"Out of Service") * ('Fleet Master'!$G$2:$G$100<>"Maintenance") * ('Fleet Master'!$A$2:$A$100<>""), ""))} -> 30 | F11: {=IF(OR(A11="No Cars Available", $C$5=""), "",_xlfn.ANCHORARRAY( E11) * $C$4)} -> 150
A12: C002 | B12: Jetta SA | C12: GRI | D12: AB853 SA | E12: 30 | F12: 150
A13: C003 | B13: Polo | C13: BEYAZ | D13: AB027UH | E13: 30 | F13: 150
A14: C004 | B14: Tiquan | C14: SİYAH | D14: AB034UH | E14: 30 | F14: 150
A15: C005 | B15: Toura 6Ri | C15: FÜME | D15: AB-KE | E15: 40 | F15: 200
A16: C006 | B16: Opel (Manual) | C16: KAHVE | D16: AB992PD | E16: 40 | F16: 200
A17: C007 | B17: Touran 7Person | C17: SİYAH | D17: AB-GF | E17: 40 | F17: 200
A18: C008 | B18: Touran 7Person | C18: SİYAH | D18: AB-GF | E18: 40 | F18: 200
A19: C009 | B19: Touran 7Person | C19: MAVİ | D19: AB-ZR | E19: 0 | F19: 0
A20: C010 | B20: 0 | C20: 0 | D20: 0 | E20: 0 | F20: 0
A21: C011 | B21: 0 | C21: 0 | D21: 0 | E21: 0 | F21: 0
A22: C012 | B22: 0 | C22: 0 | D22: 0 | E22: 0 | F22: 0
A23: C013 | B23: 0 | C23: 0 | D23: 0 | E23: 0 | F23: 0
A24: C014 | B24: 0 | C24: 0 | D24: 0 | E24: 0 | F24: 0
A25: C015 | B25: 0 | C25: 0 | D25: 0 | E25: 0 | F25: 0
